{
  "products": 
  [{"id":1,"name":"Cherries - Seedless","inventory":92,"category":"fruit"},
{"id":2,"name":"Mushroom - Morels, Dry","inventory":10,"category":"vegetable"},
{"id":3,"name":"Beets - Golden","inventory":10,"category":"vegetable"},
{"id":4,"name":"Salad - Mixed, Veg","inventory":39,"category":"vegetable"},
{"id":5,"name":"Potatoes - Purple, Organic","inventory":31,"category":"vegetable"},
{"id":6,"name":"Cheese - Parmigiano Reggiano","inventory":29,"category":"dairy"},
{"id":7,"name":"Fish - Frozen","inventory":56,"category":"meat"},
{"id":8,"name":"Milk - Two Percent","inventory":4,"category":"dairy"},
{"id":9,"name":"Squash - Magda","inventory":28,"category":"vegetable"},
{"id":10,"name":"Bananas - Yellow","inventory":70,"category":"fruit"},
{"id":11,"name":"Nantucket - Pomegranate Pear","inventory":3,"category":"fruit"},
{"id":12,"name":"Cheese - Mascarpone","inventory":3,"category":"dairy"},
{"id":13,"name":"Cheese - Goat With Herbs","inventory":70,"category":"dairy"},
{"id":14,"name":"Fish - Salmon","inventory":59,"category":"meat"},
{"id":15,"name":"Mushroom - King Trumpet","inventory":89,"category":"vegetable"},
{"id":16,"name":"Beef - Ground","inventory":3,"category":"meat"},
{"id":17,"name":"Seaweed - Green Sheets","inventory":77,"category":"vegetable"},
{"id":18,"name":"Split Peas - Yellow, Dry","inventory":35,"category":"vegetable"},
{"id":19,"name":"Juice - Lagoon Mango","inventory":54,"category":"fruit"},
{"id":20,"name":"Squash - Chayote","inventory":46,"category":"vegetable"},
{"id":21,"name":"Beef - Kobe Striploin","inventory":81,"category":"meat"},
{"id":22,"name":"Pork - Bacon","inventory":44,"category":"meat"},
{"id":23,"name":"Pork - European Side Bacon","inventory":56,"category":"meat"},
{"id":24,"name":"Pepper - Cayenne","inventory":99,"category":"vegetable"},
{"id":25,"name":"Cheese - Feta","inventory":84,"category":"dairy"}]
}